unicaps/__init__.py
unicaps/__version__.py
unicaps/_solver.py
unicaps/_solver_async.py
unicaps/captcha.py
unicaps/common.py
unicaps/exceptions.py
unicaps/proxy.py
unicaps/_captcha/__init__.py
unicaps/_captcha/base.py
unicaps/_captcha/capy.py
unicaps/_captcha/funcaptcha.py
unicaps/_captcha/geetest.py
unicaps/_captcha/geetest_v4.py
unicaps/_captcha/hcaptcha.py
unicaps/_captcha/image.py
unicaps/_captcha/keycaptcha.py
unicaps/_captcha/recaptcha_v2.py
unicaps/_captcha/recaptcha_v3.py
unicaps/_captcha/text.py
unicaps/_captcha/tiktok.py
unicaps/_misc/__init__.py
unicaps/_misc/proxy.py
unicaps/_service/__init__.py
unicaps/_service/anti_captcha.py
unicaps/_service/azcaptcha.py
unicaps/_service/base.py
unicaps/_service/captcha_guru.py
unicaps/_service/cptch_net.py
unicaps/_service/deathbycaptcha.py
unicaps/_service/rucaptcha.py
unicaps/_service/twocaptcha.py
unicaps/_transport/__init__.py
unicaps/_transport/base.py
unicaps/_transport/http_transport.py
unicaps-1.3.0.dist-info/LICENSE
unicaps-1.3.0.dist-info/METADATA
unicaps-1.3.0.dist-info/WHEEL
unicaps-1.3.0.dist-info/top_level.txt
unicaps-1.3.0.dist-info/RECORD
