Metadata-Version: 2.1
Name: unicaps
Version: 1.3.0
Summary: Universal CAPTCHA Solver for humans
Home-page: https://github.com/sergey-scat/unicaps
Author: Sergey Scat
Author-email: py.unicaps@gmail.com
Classifier: Development Status :: 5 - Production/Stable
Classifier: Intended Audience :: Developers
Classifier: License :: OSI Approved :: Apache Software License
Classifier: Operating System :: OS Independent
Classifier: Programming Language :: Python :: 3
Classifier: Programming Language :: Python :: 3.7
Classifier: Programming Language :: Python :: 3.8
Classifier: Programming Language :: Python :: 3.9
Classifier: Programming Language :: Python :: 3.10
Classifier: Programming Language :: Python :: 3.11
Requires-Python: >=3.7
License-File: LICENSE
Requires-Dist: httpx >=0.22.0
Requires-Dist: enforce-typing >=1.0.0
